rezdy_api_for_suppliers_client/__init__.py
rezdy_api_for_suppliers_client/api/__init__.py
rezdy_api_for_suppliers_client/api/availability/__init__.py
rezdy_api_for_suppliers_client/api/availability/batch_update_availability.py
rezdy_api_for_suppliers_client/api/availability/check_availability.py
rezdy_api_for_suppliers_client/api/availability/create_availability.py
rezdy_api_for_suppliers_client/api/availability/delete_session_starting_at.py
rezdy_api_for_suppliers_client/api/availability/update_availability_starting_at.py
rezdy_api_for_suppliers_client/api/bookings/__init__.py
rezdy_api_for_suppliers_client/api/bookings/cancel_booking.py
rezdy_api_for_suppliers_client/api/bookings/create_booking.py
rezdy_api_for_suppliers_client/api/bookings/get_booking.py
rezdy_api_for_suppliers_client/api/bookings/quote_booking.py
rezdy_api_for_suppliers_client/api/bookings/search_bookings.py
rezdy_api_for_suppliers_client/api/bookings/update_booking.py
rezdy_api_for_suppliers_client/api/categories/__init__.py
rezdy_api_for_suppliers_client/api/categories/add_product.py
rezdy_api_for_suppliers_client/api/categories/get_category.py
rezdy_api_for_suppliers_client/api/categories/get_category_products.py
rezdy_api_for_suppliers_client/api/categories/remove_product.py
rezdy_api_for_suppliers_client/api/categories/search_categories.py
rezdy_api_for_suppliers_client/api/companies/__init__.py
rezdy_api_for_suppliers_client/api/companies/get_company_by_alias.py
rezdy_api_for_suppliers_client/api/companies/get_company_by_name.py
rezdy_api_for_suppliers_client/api/customers/__init__.py
rezdy_api_for_suppliers_client/api/customers/create_customer.py
rezdy_api_for_suppliers_client/api/customers/delete_customer.py
rezdy_api_for_suppliers_client/api/customers/get_customer.py
rezdy_api_for_suppliers_client/api/customers/search_customers.py
rezdy_api_for_suppliers_client/api/extra/__init__.py
rezdy_api_for_suppliers_client/api/extra/create_extra.py
rezdy_api_for_suppliers_client-1.0.1.dist-info/WHEEL
rezdy_api_for_suppliers_client-1.0.1.dist-info/METADATA
rezdy_api_for_suppliers_client-1.0.1.dist-info/RECORD
